Kees-0.1.10.dist-info/DESCRIPTION.rst
Kees-0.1.10.dist-info/METADATA
Kees-0.1.10.dist-info/RECORD
Kees-0.1.10.dist-info/WHEEL
Kees-0.1.10.dist-info/entry_points.txt
Kees-0.1.10.dist-info/metadata.json
Kees-0.1.10.dist-info/top_level.txt
kees/__init__.py
kees/kees.py
