Metadata-Version: 2.0
Name: Kees
Version: 0.1.10
Summary: Translate words to or from Dutch
Home-page: https://github.com/proprefenetre/kees
Author: C. Eigenraam
Author-email: proprefenetre@gmail.com
License: MIT
Keywords: thesaurus translate translation dictionary Dutch
Platform: UNKNOWN
Requires-Dist: beautifulsoup4
Requires-Dist: lxml
